test/__init__.py
test/test_pipelines_data.py
test/test_pipelines_manager.py
test/test_pipelines_source.py
test/test_transforms_scd2.py
xdbutils/__init__.py
xdbutils/datalakehouse.py
xdbutils/deprecation.py
xdbutils/pipelines_pre_14_3_lts.py
xdbutils/pipelines/__init__.py
xdbutils/pipelines/data.py
xdbutils/pipelines/deprecation.py
xdbutils/pipelines/management.py
xdbutils/pipelines/source.py
xdbutils/transforms/__init__.py
xdbutils/transforms/scd2.py
xdbutils-0.0.2.dist-info/LICENSE
xdbutils-0.0.2.dist-info/METADATA
xdbutils-0.0.2.dist-info/WHEEL
xdbutils-0.0.2.dist-info/top_level.txt
xdbutils-0.0.2.dist-info/RECORD
