Metadata-Version: 2.1
Name: xdbutils
Version: 0.0.2
Summary: Utilities for Databricks
Home-page: https://github.com/henrikbulldog/xdbutils
Author: Henrik Thomsen
Author-email: henrik.thomsen.dk@gmail.dk
Project-URL: Bug Tracker, https://github.com/henrikbulldog/xdbutils/issues
Classifier: Programming Language :: Python :: 3
Classifier: License :: OSI Approved :: The Unlicense (Unlicense)
Classifier: Operating System :: OS Independent
Requires-Python: >=3.9
License-File: LICENSE
Requires-Dist: pyspark
